sqnm/__init__.py
sqnm/line_search/__init__.py
sqnm/line_search/armijo_line_search.py
sqnm/line_search/prob_line_search.py
sqnm/line_search/strong_wolfe_line_search.py
sqnm/optim/__init__.py
sqnm/optim/lbfgs.py
sqnm/optim/mbbfgs.py
sqnm/optim/olbfgs.py
sqnm/optim/scbfgs.py
sqnm/optim/sgd_with_ls.py
sqnm/optim/sqn_base.py
sqnm/optim/sqnhv.py
sqnm/utils/__init__.py
sqnm/utils/bvn.py
sqnm/utils/gaussian_process.py
sqnm/utils/matrix.py
sqnm/utils/param.py
sqnm-0.0.2.dist-info/licenses/LICENSE
sqnm-0.0.2.dist-info/METADATA
sqnm-0.0.2.dist-info/WHEEL
sqnm-0.0.2.dist-info/top_level.txt
sqnm-0.0.2.dist-info/RECORD
