Metadata-Version: 2.4
Name: sqnm
Version: 0.0.2
Summary: Stochastic Quasi-Newton Methods
Author-email: Limao Chang <80520563+LimaoC@users.noreply.github.com>
Maintainer-email: Limao Chang <80520563+LimaoC@users.noreply.github.com>
License-Expression: MIT
Project-URL: Repository, https://github.com/LimaoC/sqnm.git
Requires-Python: >=3.12
License-File: LICENSE
Requires-Dist: numpy>=2.3.3
Requires-Dist: scipy>=1.15.3
Requires-Dist: torch>=2.7.1
Dynamic: license-file
